smartchunks/__init__.py
smartchunks/smartchunks.py
smartchunks-0.1.1.dist-info/licenses/LICENSE
smartchunks-0.1.1.dist-info/METADATA
smartchunks-0.1.1.dist-info/WHEEL
smartchunks-0.1.1.dist-info/top_level.txt
smartchunks-0.1.1.dist-info/RECORD
