Metadata-Version: 2.4
Name: smartchunks
Version: 0.1.1
Summary: Advanced Python chunking with stride, filtering, and expressions
Author: Maurya Allimuthu
Author-email: catchmaurya@example.com
License: MIT
Classifier: Programming Language :: Python :: 3
Classifier: License :: OSI Approved :: MIT License
Classifier: Operating System :: OS Independent
Requires-Python: >=3.7
License-File: LICENSE
Dynamic: author
Dynamic: author-email
Dynamic: classifier
Dynamic: description
Dynamic: description-content-type
Dynamic: license
Dynamic: license-file
Dynamic: requires-python
Dynamic: summary
